{"recover": "g g G G G G G G w w G R g G E G G R G g E W G R G G G G E R G G g E G G G w G g G G G R g g g G G G g G g M E w M G G g G G E G G g G G G g E G g G G R G G g G G G G G g G G G G G G G E p g G E W G g g [PAD] E E G G G E E g g G G G G G G D G G g G g G G W g [PAD] p W G g G T E G g S g g [PAD] E G W W g G G g G T [PAD] G G G E G g G E G D g G G G G G G E [PAD] g G G G G G E [PAD] G G [SEP]", "reference": "[CLS] M A R S N K P V N P G A E N A L D R M K F E I A S E L G I A E T V R Q N G W A T M T S A D C G R V G G Q M V R R M I E Q Y E S S I S N T Q Q [SEP]", "source": "[CLS] d p p d p a d p d n v c p v v l v v l l l v l c v v v v n n v v c v p p n p v p d d p v s v v s s v v v s v v v v v v v v v v v v v v v v d [SEP] [SEP]", "af_id": "AF-A0A402BT90-F1"}
{"recover": "E M G g g G G G g G g G G G g g G g G G G G G g G G G G G H G G G G G G G E G g G G W G w g G E E G G G G G g g G G G G G G W E G g G g G G W G G G E G g G G E G g G G g g E G W W E D G [PAD] G g G G G G g G g G E G W g G G G G G G G [PAD] g G G G G G E g G G [SEP]", "reference": "[CLS] M H P F N L Q G A Y S R P G E L W E R A K G Q D G T H E G W Y K G A V E Y W D K Q E A S Y N G V L G G F G H V S S F D I G D S R E M L R K V R S R P G Q H R D P T S A S P P G A H E S Q V F K T H L K A A A G G K R K L T A V D C G A G V G R V T Q E L L [SEP]", "source": "[CLS] d d p p d c p p d d p d l v v v l q v c a d p v r d n p v l l v v v l v v l l p f d l d c c r v v v n v s v c l v v v l v v v q v v v v c l q p p d l p p d d p p d d d d p c s v l s v v l n v v v v c v v v v n d w a e e e d a q c q l v s c v l s p d [SEP] [SEP]", "af_id": "AF-A0A0D2MXF2-F1"}
{"recover": "w M G g g G G G W G g G G G g g G g G G R G G g G G G G G g G G g G G g G g G g G G W G g g [PAD] E E G W p G G g g G G G G G G W g G H R g G G W g G p W G g G G E G E S g g g E G W W G G G g G T g G G [PAD] G G g G g G W G G R G G G G E [PAD] g G G G G G E [PAD] G G G", "reference": "[CLS] M G A S R M V S I A Q K V G L T E T L H S N N Y T I L C P L N S A L E S F D V K Y K R K K N Q L K K N V K L T K K R K L Q K S K L S D W I T S H M I Q G F H K M D E L S D D R K M Q A V N Q A T K I R F N I Y Y N P E K V V T A N C I P I V S G D H F A R [SEP]", "source": "[CLS] d q q v v v v v l c v l l v c p v v l v p f a k e f a g e g n v q c p v v v v v v v v v v v v l v p d p v n p v v v v v v s v v s v l q r q q r m a g d e d f p v n d d a q d w g q g r s n q a i w g w h w d p p p h t f i d t q p w t q p a w q p d d p [SEP] [SEP]", "af_id": "AF-A0A087U7Y0-F1"}
{"recover": "g G G G R g G G G g G G G g M E E M G g g G G G W G g G G G G E G g G G R G G g G G G G G g G g G G S E G G G G R G W G g g [PAD] G W G W G E G g g G G G G G G W G G g G G G G W g g G W G g G G E G E G g [PAD] g G G W W G G G g G T [PAD] G G G G G G G g G W G W G G G G G G [PAD] g G G G G G G [PAD] G G G", "reference": "[CLS] M I G S A P T M A A A D Y P Q S T T S A A Q I K P L H G P C Q T P G Y V N T S S G C M S P E E M N H H N N C D M Y G D L A L A G G L L G A A G G L L A I I P E P V T T F V G G I V G L V G F G G L A A G T I A Y I G N D C [SEP]", "source": "[CLS] d d d d d p p p p p p p p v p p p p p v p p p p q p d d d p p d p q w d q d p v g t d h p v v v v l v v v l v v l v v q l v q l q v q l v q l c v q l p p p d p v s v v s s v v s n v r s v v s n v v s v c v n v v s v d [SEP] [SEP]", "af_id": "AF-A0A6N8XWW7-F1"}
{"recover": "G M G G g G G G E G g G G G G E G G G G G G G g G G G G G H G G G G G g G E G E G G W G G g S E E G W G E E g g G G G w E G G E G g G G G G W E G G E G g G G E G E S g g g E G W W G G G g E T [PAD] G G G G G G G E G D g G G p G G W E [PAD] g G G G G G E g G G [SEP]", "reference": "[CLS] M R R T P L L A L I L L P A T L G L A A L R P Q L A P S A P P S P T P L A S V S P A P S L S P S P L S S P S A L P P G A P T P S P S G A P L A T P L S S P T P T P T P V P I E L S P A S A L V P V G S S V Q V A V G N T L G T V T L T G G N P Q L A N V T [SEP]", "source": "[CLS] d d d d d d d d d d d d d d d d d d d d d d d d d d d d d d d d d d d d d d d d d d d d d d d d d d d d d d d d d d d d d d d d d d d d d d d d d d d d d d p d p d q d a k d w v v l e e e a e a q g k d k i a i p d a d a d k d k d w d d v q a w d w d [SEP] [SEP]", "af_id": "AF-E6Q3L3-F1"}
{"recover": "g g E G G G E n w g g g G G G G G E E E E g G G G G G E E G g p E G G G w W g g G G R g G G G G G g G g M E E M G g g G G G W g g G G G g E G g G G R G G g G G G G G g G G G G G E G E p G G G W G g g g E W G W G E G g g G G G E G G D G G g G G G G W g G p E G g G G E G g [PAD] g g g E D W W g G G g G E [PAD] G G G G G G G E G D g G G G G G G E [PAD] g G G G G G E g G G [SEP]", "reference": "[CLS] M C K L S C Y G L S P D A I A D V L D K D T R T I A T W Q K G V A N K S N R F H D F V C L S I T L T V L F V Q L D E L W S F L R T E V T Q P H [SEP]", "source": "[CLS] d v v c v v v v d d l v n v c v v v v h d s v v s v v v v v v v v v v v v v v v v v v v v v v v v v v v v v v v v v v v v v v v v c v v d p d [SEP] [SEP]", "af_id": "AF-A0A1R4HBK2-F1"}
{"recover": "g G g G G g g g G G p G G E w w G E p G E G G G E E E W G g g G G G E R G G p E G G G g G G g E R R g G G g g G g G E M E w M G E g i G G g G g G G G G E G W G G g G G g G G G G G g G G g G G g G g p g G G W G g g g G E G D G E G g E G G G G G G D g G g G G G G W g [PAD] p E G g G G E G E G g g g G E E W g G G g G T [PAD] G G G G G g G E w W g G G G g W G G W g G G G G G E [PAD] G G [SEP]", "reference": "[CLS] M A P K K K A K K K A V K R A K K T L K K A K K K V S M A K K K V T R A K K T L K K A K K K V A K A K K R V T K A K K K K K K R [SEP]", "source": "[CLS] d p p v v v v v v v v v v v v v v v v v v v v v v v v v v v v v v v v v v v v v v v v v v v v v v v v v v v v v v v v v v v v d [SEP] [SEP]", "af_id": "AF-A0A2D6KTW7-F1"}
{"recover": "E M G g g E G E W G g G G G G E G W G G g G G g G G G G G G G S G G G G G E G G G G W G g g [PAD] G E G W G G G g g G G G E G w W g g H G g G G W E G G g G g G G E G g S g g g E G W W g G G g G T [PAD] G G G G G g G g G D G G G G g G G E [PAD] g G G G G G E [PAD] G G [SEP]", "reference": "[CLS] M V R S L Y D C P E I P I G P D G K L Y R V V V A T H Q A S N K K S P I G V T R K G V V Y E L F F T N L P Q H A F T A C D V V E L Y L H R G A F E P V L S D E D K E Q D P D R W C S H A A W G Q E A W Q V I S Q W T W N L R L E L G H Q L K P Q P L R T T [SEP]", "source": "[CLS] d d w d k d w d a f a q d d p v r h g w i k i k i k d f d d p d d d p a a d d d p r m g i h i d t d p d d c q f a p s v n s v v v v v c v v v v v v v v v v l c v v l v l v p d p d p d p v v s v v s n v v s v v v v v v c v v v v c v v p p d p p d d d [SEP] [SEP]", "af_id": "AF-A0A5A5TLM6-F1"}
{"recover": "E M G G g G G G g G g G G G G g G g G G G G G g G G G G G G G G g G G g G E G g G G W G g g G E W G G G G G g E G G G G G G D G G g G g g G W g g E E G g G D E G E S g g g E R W W G G G g G T [PAD] G G G G G G G E G W g G G G g G G E [PAD] g G G G G G E [PAD] G G [SEP]", "reference": "[CLS] M E K P R Y Q S V T I P I I L S F L L I I I T F S Y D I C T A I D V E Q D E L G A L I N A F V P L V L G V L S L V I M A M V L I F S R K E K I A F Y T L I F L G A V N L A T A V F L K F N F K D F S P L N S N H D L T T S K V L L S S V L T P I N E R S K [SEP]", "source": "[CLS] d d d d p p l p p v v v v l l v l l v v l l v v l l v l q c p d d c q q a q p l n l c s n p v s v v l s v v l s v v l v v c s v p d p d p v v s v v s s v v s s c v s n v v s v v s n v v s d t p q l v p p p p p c v v v v v v v v p p p d p d p p d p q [SEP] [SEP]", "af_id": "AF-A0A1G8J9F3-F1"}
{"recover": "R M G g g i G E T G g p G G g g G g G G R G G g G G G G G g G G G G G G G E G G G G W G w g G E W G W g G G g g G G G E E G D G G g G G G G W G G G E G g G G E G E G g g g G G W W G G G g G T [PAD] G G G G G G G g G W G G G G G G G E [PAD] g G G G G G E [PAD] G G [SEP]", "reference": "[CLS] M N Y L L V L G T L V A F C E S Q S I P E F C L L P K N E G K G S T F N F A L Y Y D A A Q D L C S P F I Y K G E G G N G N R F A N E R D C M R N C S S N A E K F Y P M D A S L A C H F K K E S G K C G G Q L L R F Y Y D P F N A K C K K F Q W T G C V G N [SEP]", "source": "[CLS] d d d d d d d d d p p p p p p p v d q d v q l v d d w d q a d a q d f d w w w f h d p v v l f i d i d g h r p d d t t p r t h p d r l v n n v r g p p c s c v f e n p l l l v q l p d d w d q d d a q a f q w w w f h d q q v r a i d i d t h r r g d g g [SEP] [SEP]", "af_id": "AF-H3C3T1-F1"}
